buildrunner/SourceDockerfile
buildrunner/__init__.py
buildrunner/cli.py
buildrunner/config/__init__.py
buildrunner/config/fetch/__init__.py
buildrunner/config/fetch/file.py
buildrunner/config/fetch/github.py
buildrunner/config/fetch/http.py
buildrunner/config/jinja_context.py
buildrunner/config/loader.py
buildrunner/config/models.py
buildrunner/config/models_step.py
buildrunner/config/validation.py
buildrunner/docker/__init__.py
buildrunner/docker/builder.py
buildrunner/docker/daemon.py
buildrunner/docker/image_info.py
buildrunner/docker/importer.py
buildrunner/docker/multiplatform_image_builder.py
buildrunner/docker/runner.py
buildrunner/errors.py
buildrunner/loggers.py
buildrunner/provisioners/__init__.py
buildrunner/provisioners/salt.py
buildrunner/provisioners/shell.py
buildrunner/sshagent/SSHAgentProxyImage/Dockerfile
buildrunner/sshagent/SSHAgentProxyImage/login.sh
buildrunner/sshagent/SSHAgentProxyImage/run.sh
buildrunner/sshagent/__init__.py
buildrunner/steprunner/__init__.py
buildrunner/steprunner/tasks/__init__.py
buildrunner/steprunner/tasks/build.py
buildrunner/steprunner/tasks/push.py
buildrunner/steprunner/tasks/pypipush.py
buildrunner/steprunner/tasks/remote.py
buildrunner/steprunner/tasks/run.py
buildrunner/utils.py
buildrunner-3.19.1203.dist-info/WHEEL
buildrunner-3.19.1203.dist-info/entry_points.txt
buildrunner-3.19.1203.dist-info/METADATA
buildrunner-3.19.1203.dist-info/RECORD
