Metadata-Version: 2.3
Name: buildrunner
Version: 3.19.1203
Summary: Docker-based build tool
Author: Adobe
Author-email: Adobe <noreply@adobe.com>
License: MIT
Requires-Dist: jinja2>=2.11.2
Requires-Dist: pyyaml>=6.0
Requires-Dist: bcrypt>=3.2.0
Requires-Dist: decorator>=5.1.0
Requires-Dist: docker>=6.1.2
Requires-Dist: fabric>=2.5.0
Requires-Dist: paramiko>=2.10.3,<4.0.0
Requires-Dist: requests>=2.27.0
Requires-Dist: twine>=6.1.0
Requires-Dist: vcsinfo>=2.1.105
Requires-Dist: graphlib-backport>=1.0.3
Requires-Dist: timeout-decorator>=0.5.0
Requires-Dist: python-on-whales>=0.70.1
Requires-Dist: pydantic>=2.11.7
Requires-Dist: retry2>=0.9.5
Requires-Dist: colorlog>=6.8.0
Requires-Dist: rich>=13
Requires-Dist: portalocker>=2.10.1
Requires-Python: >=3.9
Project-URL: Homepage, https://github.com/adobe/buildrunner
